[
  {
    "job_id": "naukri_5_1770635136",
    "title": "Senior Data Scientist - Computer Vision",
    "company": "Samsung R&D",
    "score": 0.3717,
    "skill_match": 0.75,
    "matching_skills": [
      "python",
      "opencv",
      "computer vision",
      "pytorch"
    ],
    "missing_skills": [
      "deep learning"
    ]
  },
  {
    "job_id": "naukri_2_1770635136",
    "title": "Data Scientist",
    "company": "Jio Platforms",
    "score": 0.308,
    "skill_match": 0.4,
    "matching_skills": [
      "python",
      "sql",
      "predictive modeling"
    ],
    "missing_skills": [
      "aws",
      "machine learning",
      "deep learning"
    ]
  }
]